pyfsig/__init__.py
pyfsig/constants.py
pyfsig/interface.py
pyfsig-1.1.1.dist-info/METADATA
pyfsig-1.1.1.dist-info/WHEEL
pyfsig-1.1.1.dist-info/licenses/LICENSE
pyfsig-1.1.1.dist-info/RECORD
