Metadata-Version: 2.4
Name: pyfsig
Version: 1.1.1
Summary: A library for identifying files form their magic byte signature.
License-Expression: MIT
License-File: LICENSE
Requires-Python: >=3.9
